{
    "AX": {
        "error": 0.0118889091360014, 
        "filter_outliers_dict": {
            "filter_outliers": true, 
            "iterations": 1, 
            "std_devs": 2
        }, 
        "fit": "average", 
        "value": -0.12579915385070226
    }, 
    "H1": {
        "error": 0.00998137547284731, 
        "filter_outliers_dict": {
            "filter_outliers": true, 
            "iterations": 1, 
            "std_devs": 2
        }, 
        "fit": "average", 
        "value": -0.11993191399639842
    }, 
    "H2": {
        "error": 0.009432004758015951, 
        "filter_outliers_dict": {
            "filter_outliers": true, 
            "iterations": 1, 
            "std_devs": 2
        }, 
        "fit": "average", 
        "value": -0.18165040724804296
    }, 
    "L1": {
        "error": 0.0109379197069905, 
        "filter_outliers_dict": {
            "filter_outliers": true, 
            "iterations": 1, 
            "std_devs": 2
        }, 
        "fit": "average", 
        "value": -0.14060243335803507
    }, 
    "L2(CDD)": {
        "error": 0.0, 
        "filter_outliers_dict": {
            "filter_outliers": true, 
            "iterations": 1, 
            "std_devs": 2
        }, 
        "fit": "average", 
        "value": 0.0
    }
}